filearranger/__init__.py
filearranger-0.0.1.dist-info/LICENSE
filearranger-0.0.1.dist-info/METADATA
filearranger-0.0.1.dist-info/WHEEL
filearranger-0.0.1.dist-info/top_level.txt
filearranger-0.0.1.dist-info/RECORD
