Metadata-Version: 2.1
Name: filearranger
Version: 0.0.1
Summary: I've built this for fun.
Author: Shane Sarzedas
Author-email: Shane.sarzedas@gmail.com
License: UNKNOWN
Platform: UNKNOWN
Classifier: Programming Language :: Python :: 3
Classifier: License :: OSI Approved :: MIT License
Classifier: Operating System :: OS Independent
Requires-Python: >=3.9
License-File: LICENSE
